Topsis/__init__.py
Topsis/__main__.py
Topsis_Archit_101903054-1.1.0.dist-info/LICENSE
Topsis_Archit_101903054-1.1.0.dist-info/METADATA
Topsis_Archit_101903054-1.1.0.dist-info/WHEEL
Topsis_Archit_101903054-1.1.0.dist-info/entry_points.txt
Topsis_Archit_101903054-1.1.0.dist-info/top_level.txt
Topsis_Archit_101903054-1.1.0.dist-info/RECORD
