Metadata-Version: 2.1
Name: Topsis-Archit-101903054
Version: 1.1.0
Summary: Calculates TOPSIS on the given dataset!
Home-page: https://github.com/Snehil-21/Topsis-Snehil-101903064
Author: Archit Kapoor
Author-email: architkapoor13@gmail.com
License: MIT
Platform: UNKNOWN
Classifier: License :: OSI Approved :: MIT License
Classifier: Programming Language :: Python :: 3.8
Classifier: Programming Language :: Python :: 3.9
Classifier: Programming Language :: Python :: 3.10
Requires-Dist: pandas
